{
  "as_of": "2026-03-18",
  "capital": 500000,
  "pairs": {
    "DG/MOS": {
      "strategy": "mrpt",
      "param_set": "deep_dislocation",
      "direction": "long",
      "s1_shares": 1005,
      "s2_shares": -5208,
      "open_date": "2026-03-13",
      "open_s1_price": 135.635,
      "open_s2_price": 31.205,
      "days_held": 0
    },
    "GS/ALLY": {
      "direction": null
    },
    "D/MCHP": {
      "direction": null
    },
    "CART/DASH": {
      "direction": null
    },
    "CL/SRE": {
      "strategy": "mrpt",
      "param_set": "fast_signal",
      "direction": "long",
      "s1_shares": 908,
      "s2_shares": -868,
      "open_date": "2026-03-17",
      "open_s1_price": 88.84,
      "open_s2_price": 95.11,
      "days_held": 0
    },
    "MTCH/NVR": {
      "direction": null
    },
    "F/PG": {
      "strategy": "mrpt",
      "param_set": "stable_signal_quick_exit",
      "direction": "short",
      "s1_shares": -6426,
      "s2_shares": 500,
      "open_date": "2026-03-18",
      "open_s1_price": 11.94,
      "open_s2_price": 151.48,
      "days_held": 0
    }
  }
}